template_mailer/__init__.py
template_mailer/mail_merge.py
template_mailer/smtp_client.py
template_mailer-0.2.0.dist-info/AUTHORS.rst
template_mailer-0.2.0.dist-info/LICENSE.txt
template_mailer-0.2.0.dist-info/METADATA
template_mailer-0.2.0.dist-info/WHEEL
template_mailer-0.2.0.dist-info/top_level.txt
template_mailer-0.2.0.dist-info/RECORD
