Metadata-Version: 2.1
Name: template-mailer
Version: 0.2.0
Summary: Add a short description here!
Home-page: https://github.com/plysytsya/template-mailer
Author: Pavlo Lysytsya
Author-email: pavlo.lysytsya@outfittery.de
License: mit
Project-URL: Documentation, https://github.com/plysytsya/template-mailer
Platform: any
Classifier: Development Status :: 4 - Beta
Classifier: Programming Language :: Python
Provides-Extra: testing
Requires-Dist: pytest ; extra == 'testing'
Requires-Dist: pytest-cov ; extra == 'testing'
